statisticalrl_experiments/__init__.py
statisticalrl_experiments/analyzeRuns.py
statisticalrl_experiments/fullExperiment.py
statisticalrl_experiments/generictemplate.py
statisticalrl_experiments/oneRun.py
statisticalrl_experiments/parallelRuns.py
statisticalrl_experiments/plotResults.py
statisticalrl_experiments/test.py
statisticalrl_experiments/utils.py
statisticalrl_experiments-2.2507.dist-info/licenses/LICENSE
statisticalrl_experiments-2.2507.dist-info/METADATA
statisticalrl_experiments-2.2507.dist-info/WHEEL
statisticalrl_experiments-2.2507.dist-info/top_level.txt
statisticalrl_experiments-2.2507.dist-info/RECORD
