Metadata-Version: 2.4
Name: statisticalRL-experiments
Version: 2.2507
Summary: Experimentation backbone for the Statistical Reinforcement Learning project
Author-email: Odalric-Ambym Maillard <odalric.maillard@inria.fr>
License: MIT
Project-URL: Homepage, https://github.com/StatisticalRL/experiments
Requires-Python: >=3.8
License-File: LICENSE
Requires-Dist: gymnasium==1.2.0
Requires-Dist: numpy==1.24.3
Requires-Dist: joblib==1.3.2
Requires-Dist: matplotlib==3.7.2
Requires-Dist: statisticalRL-environments==2.2507
Requires-Dist: statisticalRL-learners==2.2507
Dynamic: license-file
